quizzy/__init__.py
quizzy/__main__.py
quizzy/app.py
quizzy/models.py
quizzy/quizzy.tcss
quizzy-0.6.0.dist-info/METADATA
quizzy-0.6.0.dist-info/WHEEL
quizzy-0.6.0.dist-info/entry_points.txt
quizzy-0.6.0.dist-info/licenses/LICENSE
quizzy-0.6.0.dist-info/RECORD
