Metadata-Version: 2.4
Name: quizzy
Version: 0.6.0
Summary: A Python TUI quiz app
Author-email: Jonas Ehrlich <jonas.ehrlich@gmail.com>
License-Expression: MIT
License-File: LICENSE
Requires-Python: >=3.10
Requires-Dist: pydantic>=2.10.3
Requires-Dist: pyyaml>=6.0.2
Requires-Dist: textual-serve>=1.1.1
Requires-Dist: textual>=1.0.0
